tribune/__init__.py
tribune/utils.py
tribune/version.py
tribune/sheet_import/__init__.py
tribune/sheet_import/parsers.py
tribune/tests/__init__.py
tribune/tests/conftest.py
tribune/tests/entities.py
tribune/tests/reports.py
tribune/tests/test_objects.py
tribune/tests/test_sheet_import.py
tribune/tests/test_sheet_import_parsers.py
tribune/tests/test_utils.py
tribune/tests/utils.py
tribune-0.3.0.dist-info/METADATA
tribune-0.3.0.dist-info/WHEEL
tribune-0.3.0.dist-info/top_level.txt
tribune-0.3.0.dist-info/RECORD
