Metadata-Version: 2.1
Name: tribune
Version: 0.3.0
Summary: A library for coding Excel reports in a declarative fashion
Home-page: https://github.com/level12/tribune
Author: Matt Lewellyn
Author-email: matt.lewellyn@level12.io
License: BSD
Platform: UNKNOWN
Classifier: Development Status :: 4 - Beta
Classifier: Intended Audience :: Developers
Classifier: License :: OSI Approved :: BSD License
Classifier: Operating System :: OS Independent
Classifier: Programming Language :: Python :: 3.6
Classifier: Programming Language :: Python :: 3.7
Requires-Dist: BlazeUtils
Requires-Dist: xlsxwriter
Provides-Extra: test
Requires-Dist: BlazeUtils ; extra == 'test'
Requires-Dist: SQLAlchemy ; extra == 'test'
Requires-Dist: XlsxWriter ; extra == 'test'
Requires-Dist: openpyxl ; extra == 'test'
Requires-Dist: pytest ; extra == 'test'
Requires-Dist: pytest-cov ; extra == 'test'
Requires-Dist: wrapt ; extra == 'test'
Requires-Dist: xlrd (<2) ; extra == 'test'
